translatron/__init__.py
translatron/actions.py
translatron/cli.py
translatron/record.py
translatron/test_events.py
translatron/text.py
translatron/translator.py
translatron-0.0.1.dev0.dist-info/licenses/LICENSE
translatron-0.0.1.dev0.dist-info/METADATA
translatron-0.0.1.dev0.dist-info/WHEEL
translatron-0.0.1.dev0.dist-info/entry_points.txt
translatron-0.0.1.dev0.dist-info/top_level.txt
translatron-0.0.1.dev0.dist-info/RECORD
