Metadata-Version: 2.4
Name: translatron
Version: 0.0.1.dev0
Summary: Tools for Twilio+AWS translation projects
Author-email: "David W.H. Swenson" <dwhs@hyperblazer.net>
License: MIT
Project-URL: homepage, https://github.com/dwhswenson/translatron
Project-URL: repository, https://github.com/dwhswenson/translatron
Project-URL: changelog, https://github.com/dwhswenson/translatron/releases
Keywords: translation,aws,twilio,transcription,text-to-speech
Classifier: Development Status :: 3 - Alpha
Classifier: Programming Language :: Python :: 3 :: Only
Classifier: License :: OSI Approved :: MIT License
Classifier: Intended Audience :: Developers
Requires-Python: >=3.11
License-File: LICENSE
Requires-Dist: twilio
Requires-Dist: boto3
Requires-Dist: click
Requires-Dist: pydantic
Provides-Extra: dev
Requires-Dist: pytest; extra == "dev"
Requires-Dist: pytest-cov; extra == "dev"
Requires-Dist: moto[all]; extra == "dev"
Requires-Dist: ruff; extra == "dev"
Requires-Dist: pre-commit; extra == "dev"
Requires-Dist: autorelease; extra == "dev"
Dynamic: license-file
